phone2address/__init__.py
phone2address/cli.py
phone2address-0.0.5.dist-info/.DS_Store
phone2address-0.0.5.dist-info/DESCRIPTION.rst
phone2address-0.0.5.dist-info/entry_points.txt
phone2address-0.0.5.dist-info/METADATA
phone2address-0.0.5.dist-info/metadata.json
phone2address-0.0.5.dist-info/RECORD
phone2address-0.0.5.dist-info/top_level.txt
phone2address-0.0.5.dist-info/WHEEL
