Metadata-Version: 2.0
Name: phone2address
Version: 0.0.5
Summary: phone2address is a tool for phone number address.
Home-page: https://xuanwo.org/
Author: Xuanwo
Author-email: xuanwo.cn@gmail.com
License: MIT License
Keywords: phone,address,script
Platform: UNKNOWN
Classifier: Development Status :: 4 - Beta
Classifier: Environment :: Console
Classifier: License :: OSI Approved :: MIT License
Classifier: Operating System :: MacOS
Classifier: Operating System :: POSIX
Classifier: Operating System :: POSIX :: Linux
Classifier: Operating System :: Microsoft :: Windows
Classifier: Programming Language :: Python
Classifier: Programming Language :: Python :: 3.4
Classifier: Programming Language :: Python :: 3.5
Requires-Dist: docopt
Requires-Dist: openpyxl
Requires-Dist: requests
Requires-Dist: bs4
